app/__init__.py
app/__main__.py
app/config.py
app/container.py
app/models.py
app/mqtt_client.py
app/services.py
tests/__init__.py
tests/test_config.py
tests/test_container.py
tests/test_models.py
tests/test_mqtt_client.py
tests/test_services.py
PiAlarmAdapter-0.0.1.dist-info/LICENSE
PiAlarmAdapter-0.0.1.dist-info/METADATA
PiAlarmAdapter-0.0.1.dist-info/WHEEL
PiAlarmAdapter-0.0.1.dist-info/entry_points.txt
PiAlarmAdapter-0.0.1.dist-info/top_level.txt
PiAlarmAdapter-0.0.1.dist-info/RECORD
