Metadata-Version: 2.1
Name: PiAlarmAdapter
Version: 0.0.1
Summary: Manage contact sensors and send messages with state change to MQTT Broker
Home-page: https://github.com/francescoscanferla/PiAlarmAdapter
Author: Francesco Scanferla
Author-email: info@francescoscanferla.it
Classifier: Programming Language :: Python :: 3
Classifier: License :: OSI Approved :: MIT License
Classifier: Operating System :: OS Independent
Requires-Python: >=3.11
License-File: LICENSE
Requires-Dist: dependency-injector ==4.41.0
Requires-Dist: paho-mqtt ==2.1.0
Requires-Dist: python-dotenv ==1.0.1
Requires-Dist: pydantic-settings ==2.3.3
Requires-Dist: gpiozero ==2.0.1
Requires-Dist: parameterized ==0.9.0
